README.md
setup.py
pdf_creator/__init__.py
pdf_creator/creator.py
pdf_creator.egg-info/PKG-INFO
pdf_creator.egg-info/SOURCES.txt
pdf_creator.egg-info/dependency_links.txt
pdf_creator.egg-info/requires.txt
pdf_creator.egg-info/top_level.txt
tests/__init__.py
tests/test_pdf_creator.py