Metadata-Version: 2.1
Name: pdf-creator
Version: 1.0.0
Summary: This library create pdf file
Home-page: https://github.com/liliamir/pdf_creator
Author: Lilia Mironova
Author-email: llmir@inbox.ru
License: UNKNOWN
Platform: any
Requires-Python: >=3.7
